[
    {
        "id": "693e7817f0521",
        "title": "線形代数入門",
        "image": "uploads\/1765695895_ダウンロード.jpeg",
        "faculty": "応用情報工学コース",
        "price": "0",
        "seller": "k520484x",
        "status": "sold"
    },
    {
        "title": "微積分５",
        "image": "images\/sample_book.jpg",
        "faculty": "共通教育",
        "price": "0",
        "seller": "k520111b"
    },
    {
        "title": "線形代数７",
        "image": "images\/sample_book.jpg",
        "faculty": "法学・政策学履修コース",
        "price": "0",
        "seller": "k520140u"
    },
    {
        "title": "微積分",
        "image": "images\/sample_book.jpg",
        "faculty": "共通教育",
        "price": "0",
        "seller": "k520111b"
    },
    {
        "id": "69363e7d8e067",
        "title": "微積分a",
        "image": "images\/sample_book.jpg",
        "trade_type": "free",
        "price": 0,
        "faculty": "工学部",
        "department": "",
        "course": "",
        "detail": "",
        "seller": "k520484x",
        "created_at": "2025-12-14 17:40:55",
        "sellerName": "山口哲平",
        "status": "sold"
    },
    {
        "id": "693e810f2f958",
        "title": "システム英単語",
        "image": "images\/sample_book.jpg",
        "trade_type": "paid",
        "price": 2000,
        "faculty": "工学部",
        "department": "",
        "course": "",
        "detail": "",
        "seller": "k520111b",
        "created_at": "2025-12-14 18:19:11",
        "sellerName": "奥山颯太",
        "status": "active"
    },
    {
        "id": "693e8e45d5998",
        "title": "システム英単語",
        "image": "images\/sample_book.jpg",
        "trade_type": "free",
        "price": 0,
        "faculty": "工学部",
        "department": "",
        "course": "",
        "detail": "システム英単語じゃないよー！",
        "seller": "k520484x",
        "created_at": "2025-12-14 19:15:33",
        "sellerName": "山口哲平"
    },
    {
        "id": "693f69c6f1d0d",
        "title": "線形代数入門",
        "image": "images\/sample_book.jpg",
        "trade_type": "free",
        "price": 0,
        "faculty": "工学部",
        "department": "工学科",
        "course": "",
        "detail": "kaaaaaaaaaaaaaa",
        "seller": "abcdefgh",
        "created_at": "2025-12-15 10:52:06",
        "sellerName": "abcdefgh"
    },
    {
        "id": "6948a7fac26ed",
        "title": "bisekibunn",
        "image": "images\/sample_book.jpg",
        "trade_type": "free",
        "price": 0,
        "faculty": "工学部",
        "department": "工学科",
        "course": "コンピュータ科学コース",
        "detail": "waaa",
        "seller": "k520111b",
        "created_at": "2025-12-22 11:07:54",
        "sellerName": "奥山颯太"
    },
    {
        "id": "6948a9f92cd53",
        "title": "biseki2",
        "image": "images\/20251222111622_スクリーンショット 2025-12-12 001448.png",
        "trade_type": "free",
        "price": 0,
        "faculty": "",
        "department": null,
        "course": null,
        "detail": "",
        "seller": "k520111b",
        "created_at": "2025-12-22 11:16:25",
        "sellerName": "奥山颯太",
        "trade": "free"
    },
    {
        "id": "6948af90b42f8",
        "title": "せんけい",
        "image": "images\/20251222114013_スクリーンショット 2025-12-12 003209.png",
        "trade_type": "free",
        "price": 0,
        "faculty": "",
        "department": null,
        "course": null,
        "detail": "",
        "seller": "k520111b",
        "created_at": "2025-12-22 11:40:16",
        "sellerName": "奥山颯太",
        "trade": "paid"
    },
    {
        "id": "6948b16b1b2dd",
        "title": "new せんけい",
        "image": "images\/20251222114809_スクリーンショット 2025-12-12 143028.png",
        "trade_type": "free",
        "price": 0,
        "faculty": "社会共創学部",
        "department": "環境デザイン学科",
        "course": "",
        "detail": "",
        "seller": "k520111b",
        "created_at": "2025-12-22 11:48:11",
        "sellerName": "奥山颯太"
    }
]